azure/cognitiveservices/vision/contentmoderator/__init__.py
azure/cognitiveservices/vision/contentmoderator/content_moderator_client.py
azure/cognitiveservices/vision/contentmoderator/py.typed
azure/cognitiveservices/vision/contentmoderator/version.py
azure/cognitiveservices/vision/contentmoderator/models/__init__.py
azure/cognitiveservices/vision/contentmoderator/models/_models.py
azure/cognitiveservices/vision/contentmoderator/models/_models_py3.py
azure/cognitiveservices/vision/contentmoderator/models/_paged_models.py
azure/cognitiveservices/vision/contentmoderator/operations/__init__.py
azure/cognitiveservices/vision/contentmoderator/operations/image_moderation_operations.py
azure/cognitiveservices/vision/contentmoderator/operations/list_management_image_lists_operations.py
azure/cognitiveservices/vision/contentmoderator/operations/list_management_image_operations.py
azure/cognitiveservices/vision/contentmoderator/operations/list_management_term_lists_operations.py
azure/cognitiveservices/vision/contentmoderator/operations/list_management_term_operations.py
azure/cognitiveservices/vision/contentmoderator/operations/reviews_operations.py
azure/cognitiveservices/vision/contentmoderator/operations/text_moderation_operations.py
azure_cognitiveservices_vision_contentmoderator-1.0.1.dist-info/LICENSE
azure_cognitiveservices_vision_contentmoderator-1.0.1.dist-info/METADATA
azure_cognitiveservices_vision_contentmoderator-1.0.1.dist-info/WHEEL
azure_cognitiveservices_vision_contentmoderator-1.0.1.dist-info/top_level.txt
azure_cognitiveservices_vision_contentmoderator-1.0.1.dist-info/RECORD
