Metadata-Version: 2.1
Name: azure-cognitiveservices-vision-contentmoderator
Version: 1.0.1
Summary: Microsoft Azure Cognitive Services Content Moderator Client Library for Python
Home-page: https://github.com/Azure/azure-sdk-for-python
Author: Microsoft Corporation
Author-email: azpysdkhelp@microsoft.com
License: MIT License
Keywords: azure,azure sdk
Classifier: Development Status :: 7 - Inactive
Classifier: Programming Language :: Python
Classifier: Programming Language :: Python :: 2
Classifier: Programming Language :: Python :: 2.7
Classifier: Programming Language :: Python :: 3
Classifier: Programming Language :: Python :: 3.6
Classifier: Programming Language :: Python :: 3.7
Classifier: Programming Language :: Python :: 3.8
Classifier: Programming Language :: Python :: 3.9
Classifier: Programming Language :: Python :: 3.10
Classifier: License :: OSI Approved :: MIT License
License-File: LICENSE
Requires-Dist: msrest>=0.6.21
Requires-Dist: azure-common~=1.1
Requires-Dist: azure-mgmt-core<2.0.0,>=1.2.0
Requires-Dist: azure-cognitiveservices-vision-nspkg; python_version < "3.0"
